{
  "id": "MyProgram1",
  "type" : "Program",
  "controlName" : "canvas",
  "table": [{
    "ref" : 1,
    "blockId": "myFunction1",
    "type": "ParameterNode",
    "controlName": "function-parameter",
    "value": "truth",
    "name": "active"
  },{
    "ref" : 2,
    "blockId": "myFunction1",
    "type": "ParameterNode",
    "controlName": "function-parameter",
    "value": "text",
    "name": "manager"
  },{
    "ref" : 3,
    "blockId": "myFunction-1-Body",
    "type": "ParameterNode",
    "controlName": "function-parameter",
    "value": "truth",
    "name": "active"
  }],
  "children": [{
    "id": "myFunction1",
    "type" : "Function",
    "controlName" : "function",
    "children" : [{
      "id" : "myFunction1-Name",
      "type" : "FunctionName",
      "value": "test"
    }, {
      "id" : "myFunction1-ReturnType",
      "type": "FunctionReturnType",
      "value" : "truth"
    },{
      "id": "myFunction1-Parameters",
      "type" : "FunctionParameters",
      "children" : [{
        "ref": 1,
        "blockId": "myFunction1"
      },{
        "ref": 2,
        "blockId": "myFunction1"
      }]
    }, {
      "id": "myFunction1-Body",
      "type" : "Block",
      "controlName": "block",
      "children": [{
        "id": "myFunction1-ReturnStatement",
        "type": "ReturnStatement",
        "controlName" : "return-statement",
        "children" : [{
          "id": "myExpression1",
          "type" : "EqualToExpression",
          "controlName" : "equal-to-expression",
          "left" : {
            "ref" : 3,
            "blockId": "myFunction-1-Body"
          },
          "right": {
            "id" : "myRightExpression1",
            "type" : "BooleanLiteral",
            "value" : "yes"
          }
        }]
      }]
    }]
  }]
}